stl_rs-0.1.4.dist-info/METADATA
stl_rs-0.1.4.dist-info/WHEEL
stl_rs-0.1.4.dist-info/licenses/LICENSE
stl_rs/__init__.py
stl_rs/stl_rs.abi3.so
stl_rs-0.1.4.dist-info/RECORD
