Metadata-Version: 2.4
Name: stl_rs
Version: 0.1.4
Classifier: Development Status :: 4 - Beta
Classifier: Intended Audience :: Science/Research
Classifier: License :: OSI Approved :: MIT License
Classifier: Programming Language :: Python :: 3
Classifier: Programming Language :: Python :: 3.8
Classifier: Programming Language :: Python :: 3.9
Classifier: Programming Language :: Python :: 3.10
Classifier: Programming Language :: Python :: 3.11
Classifier: Programming Language :: Python :: 3.12
Classifier: Programming Language :: Rust
Classifier: Topic :: Scientific/Engineering
License-File: LICENSE
Summary: Fast STL decomposition implemented in Rust
Keywords: time-series,stl,decomposition,statistics
Author-email: Thomas Q <thomasqsa@gmail.com>
Requires-Python: >=3.8
